zpy/__init__.py
zpy/api/__init__.py
zpy/api/cloud_handlers.py
zpy/api/http/__init__.py
zpy/api/http/errors.py
zpy/api/http/header_validator.py
zpy/api/http/request.py
zpy/api/http/response.py
zpy/api/http/serializers.py
zpy/api/http/status_codes.py
zpy/app/__init__.py
zpy/app/lifecycle.py
zpy/app/sdk.py
zpy/app/usecase.py
zpy/app/values.py
zpy/cli/__init__.py
zpy/cli/utils.py
zpy/cli/agregations/__init__.py
zpy/cli/agregations/agregations.py
zpy/cli/scaffolding/__init__.py
zpy/cli/scaffolding/boilerplates.py
zpy/cli/scaffolding/ignore.py
zpy/cli/scaffolding/placeholders.py
zpy/cloud/__init__.py
zpy/cloud/aws/__init__.py
zpy/cloud/aws/lambdax.py
zpy/cloud/aws/mocks.py
zpy/cloud/aws/queue_handler.py
zpy/cloud/aws/sqs.py
zpy/cloud/aws/wss.py
zpy/containers/MemoryCacheSystem.py
zpy/containers/Storable.py
zpy/containers/__init__.py
zpy/containers/di_container.py
zpy/logger/__init__.py
zpy/logger/structured.py
zpy/logger/utils.py
zpy/utils/__init__.py
zpy/utils/collections.py
zpy/utils/dates.py
zpy/utils/files.py
zpy/utils/funcs.py
zpy/utils/http_client.py
zpy/utils/objects.py
zpy/utils/parallel.py
zpy/utils/values.py
zpy/utils/functions/__init__.py
zpy/utils/functions/results.py
zpy/utils/tools/__init__.py
zpy/utils/tools/retryer.py
zpy_api_core-2.3.0.dist-info/licenses/LICENSE
zpy_api_core-2.3.0.dist-info/METADATA
zpy_api_core-2.3.0.dist-info/WHEEL
zpy_api_core-2.3.0.dist-info/entry_points.txt
zpy_api_core-2.3.0.dist-info/top_level.txt
zpy_api_core-2.3.0.dist-info/RECORD
