Metadata-Version: 2.4
Name: zpy-api-core
Version: 2.3.0
Summary: Helper layer for backend application development to Aws Lambda
Home-page: https://github.com/NoeCruzMW
Author: Noé Cruz | linkedin.com/in/zurckz/
Author-email: zurckz.services@gmail.com
Classifier: Programming Language :: Python :: 3.13
Classifier: License :: OSI Approved :: MIT License
Classifier: Operating System :: OS Independent
Requires-Python: >=3.13
License-File: LICENSE
Requires-Dist: marshmallow<4.0.0,>=3.23.0
Requires-Dist: marshmallow_objects==2.3.0
Requires-Dist: requests==2.32.5
Requires-Dist: Click
Requires-Dist: python-dateutil
Dynamic: author
Dynamic: author-email
Dynamic: classifier
Dynamic: description
Dynamic: description-content-type
Dynamic: home-page
Dynamic: license-file
Dynamic: requires-dist
Dynamic: requires-python
Dynamic: summary
